[
    {
        "title": "$:/plugins/tesseract/CleverNote",
        "type": "application/json",
        "text": "{\n    \"tiddlers\": {\n        \"$:/CleverNote/ui/Stylesheet\": {\n            \"text\": \"<$reveal state=\\\"$:/CurrentPlatform\\\" type=\\\"nomatch\\\" text=\\\"desktop\\\">\\n\\n.bottombarcontainer {\\n\\tposition: fixed;\\n\\twidth: 100%;\\n\\theight: 8%;\\n\\tbackground-color: #F8F8F8;\\n\\tbottom: 0;\\n\\tleft: 0;\\n\\tz-index: 2000;\\n\\tdisplay: flex;\\n\\talign-items: center;\\n\\tjustify-content: center;\\n}\\n.bottombar {\\n\\twidth: 100%;\\n\\tdisplay: flex;\\n\\talign-items: center;\\n\\tjustify-content: center;\\n}\\n\\n.leftsidebarcontainer-mobile {\\n\\tposition: fixed;\\n\\tleft: 0;\\n\\ttop: 0;\\n\\theight: 100%;\\n\\twidth: 15%;\\n       max-width: 75px;\\n\\tz-index: 1500;\\n\\tdisplay: flex;\\n\\talign-items: center;\\n\\tjustify-content: center;\\n\\tbackground-color: #F8F8F8;\\n\\t\\n}\\n\\n.leftsidebarcontainer-mobile {\\n\\tposition: fixed;\\n\\tleft: 0;\\n\\ttop: 0;\\n\\theight: 100%;\\n\\twidth: 15%;\\n\\tz-index: 1500;\\n\\tdisplay: flex;\\n\\talign-items: center;\\n\\tjustify-content: center;\\n       background-color: #F8F8F8;\\n}\\n\\n.leftsidebar-mobile {\\n\\tjustify-content: center;\\n\\tdisplay: flex;\\n\\tflex-direction: column;\\n}\\n\\n.switch-container {\\n\\tposition: fixed;\\n\\tbottom: 5px;\\n\\tleft: 5px;\\n\\tz-index: 2500;\\n}\\n\\n.zaah-listbar-container-mobile {\\n\\tposition: fixed;\\n\\tleft: 15%;\\n\\ttop: 0;\\n\\tbackground: #fff;\\n\\theight: 100%;\\n\\tz-index: 200;\\n\\tpadding: 24px 0 0 0;\\n\\twidth: 100%;\\n        overflow: auto;\\n}\\n\\n\\n@media screen and (min-width: 500px) {\\n.zaah-listbar-container-mobile {\\nleft:75px;\\n}\\n}\\n\\n.zaah-story-river {\\n\\tleft: 0;\\n\\twidth: 100%;\\n}\\n.tc-tiddler-frame {\\n\\tpadding: 28px 20px 42px 22px;\\n\\twidth: 100%;\\n}\\n\\n\\n.zaah-btn-square {\\n\\theight: 36px;\\n\\twidth: 36px;\\n}\\n\\n.searchbar-container {\\n\\tz-index:1800;\\n\\tposition: fixed;\\n\\ttop: 0;\\n\\tleft: 0;\\n\\tbackground: #f4f4f4;\\n\\twidth: 100%;\\n}\\n.searchbar {\\n\\twidth: 100%;\\n\\theight: 50px;\\n\\tz-index: 2500;\\n}\\n\\n.jd-searchbar {\\n\\twidth: calc(100% - 20px);\\n\\theight: 30px;\\n\\t\\n\\tfont-size: 16px !important;\\n\\tbackground: transparent !important;\\n\\tpadding: 0 140px 0 10px;\\n\\tmargin: 10px;\\n}\\n\\ninput.jd-searchbar {\\n        border: none;\\n\\tborder-bottom-width: medium;\\n\\tborder-bottom-style: none;\\n\\tborder-bottom-color: currentcolor;\\n\\tborder-bottom: 2px solid #5778d8;\\n}\\n\\n.searchresults-mobile {\\n\\twidth: 100%;\\n\\tpadding-left: 5%;\\n\\tpadding-bottom: 2%;\\n}\\n\\n.searchresultbuttons svg {\\n\\theight: 20px;\\n\\twidth: 20px;\\n}\\n\\n\\n\\n/* Editor Toolbar*/\\n\\n.tc-edit-tags {\\n  margin-bottom:12px\\n}\\n\\n.tc-editor-toolbar {\\n  position: -webkit-sticky;\\n  position: sticky;\\n  top: 0px; /* distance to stick from top, e.g if you use top bar */\\n  left:0;\\n  width:100%;\\n  font-size:1em;\\n  line-height:0;\\n  padding:0;\\n  border:5px solid transparent;\\n  background:white;\\n  margin-top:-11px; /* pull it up */\\n}\\n.tc-editor-toolbar:hover {\\n  border-color:white;\\n  \\n}\\n.tc-editor-toolbar button {\\n display:inline-block;\\n  padding:0px;\\n}\\n\\n\\n/* Sidebar*/\\n.zaah-listbar-container-mobile .tc-sidebar { padding: 5% 0 0 3%; }\\n\\n\\n/*Edit Template*/\\n.tc-tiddler-frame.tc-tiddler-edit-frame {\\n\\tpadding: 28px 5px 42px 5px;\\n}\\n\\n.zaah-btn-edit-template svg {\\n\\theight: 20px;\\n}\\n\\n<$reveal type=\\\"match\\\" state=\\\"$:/state/edittemplatefield\\\" text=\\\"hide\\\">\\n.tc-edit-field-add, .tc-edit-fields {display:none;}\\n\\n</$reveal>\\n\\n<$reveal type=\\\"match\\\" state=\\\"$:/state/edittemplatetype\\\" text=\\\"hide\\\">\\n.tc-type-selector {display:none;}\\n\\n</$reveal>\\n\\n.tc-block-dropdown {\\n\\tposition: fixed;\\n\\ttop: 10%;\\n\\tleft: 0;\\n\\tpadding: 2%;\\n\\twidth: 100%;\\n\\toverflow: auto;\\n\\tmax-height: 50%;\\n}\\n\\n</$reveal>\",\n            \"title\": \"$:/CleverNote/ui/Stylesheet\",\n            \"tags\": \"$:/tags/Stylesheet\",\n            \"modified\": \"20171209102717935\",\n            \"created\": \"20171207163956055\"\n        },\n        \"$:/CleverNote/ui/Searchbar\": {\n            \"text\": \"\\\\define searchresults()\\n<$action-navigate $to=<<navigateTo>>/>\\n<$action-setfield $tiddler=\\\"$:/state/mobile-searchbar\\\" $value=\\\"no\\\"/>\\n\\\\end\\n\\n\\n<$reveal state=\\\"$:/state/sidebar\\\" type=\\\"match\\\" text=\\\"no\\\">\\n<$reveal state=\\\"$:/state/mobile-searchbar\\\" type=\\\"match\\\" text=\\\"yes\\\">\\n<div class=\\\"searchbar-container\\\">\\n<div class=\\\"searchbar\\\">\\n<$edit-text tiddler=\\\"$:/temp/search\\\" type=\\\"search\\\" tag=\\\"input\\\" placeholder={{$:/language/Search/Search}} class=\\\"jd-searchbar\\\" focus=\\\"yes\\\"/>\\n</div>\\n\\n\\n<$reveal state=\\\"$:/temp/search\\\" type=\\\"nomatch\\\" text=\\\"\\\">\\n<div class=\\\"searchresults-mobile\\\">\\n<div class=\\\"searchresultbuttons\\\">\\n<$button tooltip={{$:/language/Buttons/AdvancedSearch/Hint}} aria-label={{$:/language/Buttons/AdvancedSearch/Caption}} class=\\\"tc-btn-invisible\\\">\\n<$action-setfield $tiddler=\\\"$:/temp/advancedsearch\\\" text={{$:/temp/search}}/>\\n<$action-setfield $tiddler=\\\"$:/temp/search\\\" text=\\\"\\\"/>\\n<$action-navigate $to=\\\"$:/AdvancedSearch\\\"/>\\n{{$:/core/images/advanced-search-button}}\\n</$button>\\n<$button class=\\\"tc-btn-invisible\\\" tooltip=\\\"Clear searchbar\\\">\\n<$action-setfield $tiddler=\\\"$:/temp/advancedsearch\\\" text=\\\"\\\"/>\\n<$action-setfield $tiddler=\\\"$:/temp/search\\\" text=\\\"\\\"/>\\n{{$:/core/images/close-button}}\\n</$button>\\n</div>\\n\\n<$linkcatcher actions=<<searchresults>>>\\n''Tiddlers''<br/>\\n<$list filter=\\\"[!is[system]search{$:/temp/search}sort[title]limit[250]] -[[$:/temp/search]]\\\">\\n<$link><$view field=\\\"title\\\"/></$link><br/>\\n</$list>\\n\\n\\n<br/><br/>''System''<br/>\\n<$list filter=\\\"[is[system]search{$:/temp/search}sort[title]limit[250]] -[[$:/temp/search]] -[[$:/temp/advancedsearch]]\\\">\\n<$link><$view field=\\\"title\\\"/></$link><br/>\\n</$list>\\n\\n<br/><br/>''Shadows''<br/>\\n<$list filter=\\\"[is[shadow]search{$:/temp/search}sort[title]limit[250]] -[[$:/temp/search]] -[[$:/temp/advancedsearch]]\\\">\\n<$link><$view field=\\\"title\\\"/></$link><br/>\\n</$list>\\n</$linkcatcher>\\n\\n\\n</div>\\n</$reveal>\\n</div>\\n</$reveal>\\n</$reveal>\\n\",\n            \"title\": \"$:/CleverNote/ui/Searchbar\",\n            \"tags\": \"$:/tags/MobilePageTemplate\",\n            \"modified\": \"20171209054545225\",\n            \"created\": \"20171209044039555\"\n        },\n        \"$:/CleverNote/ui/PageTemplate/Switch\": {\n            \"text\": \"<div class=\\\"switch-container\\\">\\n<div class=\\\"switch\\\">\\n\\n<$button class=\\\"zaah-btn-rounded\\\">{{$:/core/images/menu-button}}\\n<$reveal type=\\\"match\\\" state=\\\"$:/state/sidebar\\\" text=\\\"yes\\\">\\n<$action-setfield $tiddler=\\\"$:/state/sidebar\\\" $value=\\\"no\\\"/>\\n</$reveal>\\n<$reveal type=\\\"match\\\" state=\\\"$:/state/sidebar\\\" text=\\\"no\\\">\\n<$action-setfield $tiddler=\\\"$:/state/sidebar\\\" $value=\\\"yes\\\"/>\\n</$reveal>\\n</$button>\\n</div>\\n</div>\",\n            \"title\": \"$:/CleverNote/ui/PageTemplate/Switch\",\n            \"tags\": \"$:/tags/MobilePageTemplate\",\n            \"modified\": \"20171208100300137\",\n            \"created\": \"20171208042757688\"\n        },\n        \"$:/CleverNote/ui/PageTemplate/ListBar\": {\n            \"text\": \"<$reveal state=\\\"$:/state/sidebar\\\" type=\\\"match\\\" text=\\\"yes\\\" retain=\\\"yes\\\">\\n<div class=\\\"zaah-listbar-container-mobile\\\">\\n\\t<$tiddler tiddler={{$:/state/tab/sidebar}}>\\n\\t<div class=\\\"inline21caps\\\"><$transclude field=\\\"caption\\\"/></div>\\n\\t{{!!text}}\\n\\t</$tiddler>\\n</div>\\n</$reveal>\",\n            \"title\": \"$:/CleverNote/ui/PageTemplate/ListBar\",\n            \"tags\": \"$:/tags/MobilePageTemplate\",\n            \"modified\": \"20171209080120562\",\n            \"created\": \"20171208063100705\"\n        },\n        \"$:/CleverNote/ui/PageTemplate/LeftSideBar\": {\n            \"text\": \"\\\\define sidebar-config-title()\\n$:/config/sidebar/Visibility/$(currentTiddler)$\\n\\\\end\\n<$reveal state=\\\"$:/state/sidebar\\\" type=\\\"match\\\" text=\\\"yes\\\">\\n<div class=\\\"mobile-sidebar\\\">\\n<div class=\\\"leftsidebarcontainer-mobile\\\">\\n<div class=\\\"leftsidebar-mobile\\\">\\n<$list filter='[all[shadows+tiddlers]tag[$:/tags/SideBar]!has[draft.of]]'>\\n\\t\\t\\t\\t<$reveal type=\\\"nomatch\\\" state=<<sidebar-config-title>> text=\\\"hide\\\">\\n\\t\\t\\t\\t\\t<$button class=\\\"zaah-btn-rounded\\\" tooltip={{!!caption}} set=\\\"$:/state/tab/sidebar\\\" setTo=<<currentTiddler>>>\\n\\t\\t\\t\\t\\t<$transclude tiddler={{!!icon}}/>\\n\\t\\t\\t\\t\\t</$button>\\n\\t\\t\\t\\t</$reveal>\\n\\t\\t</$list>\\n</div>\\n</div>\\n</div>\\n</$reveal>\",\n            \"title\": \"$:/CleverNote/ui/PageTemplate/LeftSideBar\",\n            \"tags\": \"$:/tags/MobilePageTemplate\",\n            \"modified\": \"20171208122029757\",\n            \"created\": \"20171207170503223\"\n        },\n        \"$:/CleverNote/ui/PageTemplate/BottomBar\": {\n            \"text\": \"\\\\define pagecontrol-config-title()\\n$:/config/PageControlButtons/Visibility/$(listItem)$\\n\\\\end\\n<$reveal state=\\\"$:/state/sidebar\\\" type=\\\"match\\\" text=\\\"no\\\">\\n<div class=\\\"bottombarcontainer\\\">\\n<div class=\\\"bottombar\\\">\\n<$list filter=\\\"[all[shadows+tiddlers]tag[$:/tags/PageControls]!has[draft.of]]\\\" variable=\\\"listItem\\\">\\n\\t\\t\\t\\t\\t\\t<$reveal type=\\\"nomatch\\\" state=<<pagecontrol-config-title>> text=\\\"hide\\\">\\n\\t\\t\\t\\t\\t\\t\\t<$set name=\\\"tv-config-toolbar-class\\\" value=\\\"zaah-btn-square\\\">\\n\\t\\t\\t\\t\\t\\t\\t<$transclude tiddler=<<listItem>> mode=\\\"inline\\\"/>\\n\\t\\t\\t\\t\\t\\t\\t</$set>\\n</$reveal>\\n</$list>\\n<$set name=\\\"tv-config-toolbar-class\\\" value=\\\"zaah-btn-square\\\">\\n<$transclude tiddler=\\\"$:/CleverNote/buttons/search\\\" mode=\\\"inline\\\"/>\\n</$set>\\n</div></div>\\n</$reveal>\",\n            \"title\": \"$:/CleverNote/ui/PageTemplate/BottomBar\",\n            \"tags\": \"$:/tags/MobilePageTemplate\",\n            \"modified\": \"20171209032753905\",\n            \"created\": \"20171207133616205\"\n        },\n        \"$:/CleverNote/ui/EditTemplateOptions\": {\n            \"text\": \"<$reveal state=\\\"$:/CurrentPlatform\\\" type=\\\"nomatch\\\" text=\\\"desktop\\\">\\n<$button class=\\\"tc-btn-invisible zaah-btn-edit-template\\\" popup=\\\"$:/state/editTemplateItems\\\">{{$:/core/images/options-button}}</$button>\\n\\n<$reveal state=\\\"$:/state/editTemplateItems\\\" type=\\\"popup\\\">\\n<div class=\\\"tc-drop-down\\\" style=\\\"position: fixed;top: 10%;left: 0;width: 100%;margin: 0;\\\">\\n<$list filter=\\\"[tag[$:/tags/EditTemplateOptions]]\\\">\\n<$set name=\\\"tv-config-toolbar-class\\\" value=\\\"tc-btn-invisible\\\">\\n<$transclude/>\\n</$set>\\n</$list>\\n</div>\\n</$reveal>\\n</$reveal>\",\n            \"title\": \"$:/CleverNote/ui/EditTemplateOptions\",\n            \"tags\": \"$:/tags/EditTemplate\",\n            \"modified\": \"20171209092944991\",\n            \"created\": \"20171209084259625\"\n        },\n        \"$:/CleverNote/EditTemplateOptions/Type\": {\n            \"text\": \"<$reveal type=\\\"match\\\" state=\\\"$:/state/edittemplatetype\\\" text=\\\"show\\\">\\n\\n<$button set=\\\"$:/state/edittemplatetype\\\" setTo=\\\"hide\\\" class=\\\"tc-btn-invisible\\\">Hide type</$button>\\n\\n</$reveal>\\n<$reveal type=\\\"match\\\" state=\\\"$:/state/edittemplatetype\\\" text=\\\"hide\\\">\\n\\n<$button set=\\\"$:/state/edittemplatetype\\\" setTo=\\\"show\\\" class=\\\"tc-btn-invisible\\\">Show type</$button>\\n\\n</$reveal>\",\n            \"title\": \"$:/CleverNote/EditTemplateOptions/Type\",\n            \"tags\": \"$:/tags/EditTemplateOptions\",\n            \"modified\": \"20171209091655852\",\n            \"created\": \"20171209091552441\"\n        },\n        \"$:/CleverNote/EditTemplateOptions/Fields\": {\n            \"text\": \"<$reveal type=\\\"match\\\" state=\\\"$:/state/edittemplatefield\\\" text=\\\"show\\\">\\n\\n<$button set=\\\"$:/state/edittemplatefield\\\" setTo=\\\"hide\\\" class=\\\"tc-btn-invisible\\\">Hide fields</$button>\\n\\n</$reveal>\\n<$reveal type=\\\"match\\\" state=\\\"$:/state/edittemplatefield\\\" text=\\\"hide\\\">\\n\\n<$button set=\\\"$:/state/edittemplatefield\\\" setTo=\\\"show\\\" class=\\\"tc-btn-invisible\\\">Show fields</$button>\\n\\n</$reveal>\",\n            \"title\": \"$:/CleverNote/EditTemplateOptions/Fields\",\n            \"tags\": \"$:/tags/EditTemplateOptions\",\n            \"modified\": \"20171209091307079\",\n            \"created\": \"20171209090536631\"\n        },\n        \"$:/CleverNote/buttons/search\": {\n            \"text\": \"<$button class=\\\"zaah-btn-square\\\">{{$:/core/images/advanced-search-button}}\\n<$reveal type=\\\"match\\\" state=\\\"$:/state/mobile-searchbar\\\" text=\\\"yes\\\">\\n<$action-setfield $tiddler=\\\"$:/state/mobile-searchbar\\\" $value=\\\"no\\\"/>\\n</$reveal>\\n<$reveal type=\\\"match\\\" state=\\\"$:/state/mobile-searchbar\\\" text=\\\"no\\\">\\n<$action-setfield $tiddler=\\\"$:/state/mobile-searchbar\\\" $value=\\\"yes\\\"/>\\n</$reveal>\\n</$button>\",\n            \"title\": \"$:/CleverNote/buttons/search\",\n            \"modified\": \"20171209045420192\",\n            \"created\": \"20171209032805603\"\n        },\n        \"$:/state/edittemplatefield\": {\n            \"text\": \"hide\",\n            \"title\": \"$:/state/edittemplatefield\",\n            \"tags\": \"\",\n            \"modified\": \"20171209091423714\",\n            \"created\": \"20171209090923099\"\n        },\n        \"$:/state/edittemplatetype\": {\n            \"text\": \"show\",\n            \"title\": \"$:/state/edittemplatetype\",\n            \"tags\": \"\",\n            \"modified\": \"20171209091705925\",\n            \"created\": \"20171209091700179\"\n        },\n        \"$:/state/mobile-searchbar\": {\n            \"text\": \"no\",\n            \"title\": \"$:/state/mobile-searchbar\",\n            \"tags\": \"\",\n            \"modified\": \"20171209060725753\",\n            \"created\": \"20171209040113336\"\n        },\n        \"$:/state/sidebar\": {\n            \"text\": \"no\",\n            \"title\": \"$:/state/sidebar\",\n            \"tags\": \"\",\n            \"modified\": \"20171209092920438\",\n            \"created\": \"20171208121131791\"\n        }\n    }\n}",
        "author": "Riz",
        "core-version": "5.1.15",
        "description": "CleverNote ",
        "plugin-type": "plugin",
        "version": "0.0.2"
    }
]